{
  "id": "bard-college",
  "name": "Bard College",
  "benefit": "A small college for bards, teaching students of the bardic school of the players choice, and collecting sizable tuitions from students",
  "staff": [{ "name": "Bard", "num": 3, "cur": 0 }],
  "goldCost": 2000,
  "resourceCost":  {
    "alcohol": 0,
    "arcanum": 50,
    "cloth": 0,
    "coal": 0,
    "food": 0,
    "iron": 0,
    "leather": 100,
    "lumber": 500,
    "steel": 1000,
    "stone": 1000,
    "timber": 0,
    "sugar": 0,
    "coffee": 0,
    "clay": 0,
    "cotton": 0,
    "pottery": 0,
    "paper": 0,
    "consumergoods": 0,
    "furniture": 0,
    "brick": 9000,
    "horses": 0,
    "raremetal": 0,
    "wool": 0
  },
  "income": 250,
  "revenue": {
    "alcohol": 0,
    "arcanum": 0,
    "cloth": 0,
    "coal": 0,
    "food": 0,
    "iron": 0,
    "leather": 0,
    "lumber": 0,
    "steel": 0,
    "stone": 0,
    "timber": 0,
    "sugar": 0,
    "coffee": 0,
    "clay": 0,
    "cotton": 0,
    "pottery": 0,
    "paper": 0,
    "consumergoods": 0,
    "furniture": 0,
    "brick": 0,
    "horses": 0,
    "raremetal": 0,
    "wool": 0
  },
  "laborers": 0,
  "storage": 5000,
  "pop": 0,
  "staffpop": 0,
  "employs": 20,
  "operating": true,
  "buildtime": 1000,
  "prerequisites": [ "theater" ],
  "hide": true,
  "count": 0,
  "max": 8,
  "tags": [ "income", "faction-base" ],
  "type": "town",
  "isfarm": false
}